setup.py
django_invitable.egg-info/PKG-INFO
django_invitable.egg-info/SOURCES.txt
django_invitable.egg-info/dependency_links.txt
django_invitable.egg-info/requires.txt
django_invitable.egg-info/top_level.txt
invitable/__init__.py
invitable/forms.py
invitable/hooks.py
invitable/models.py
invitable/tests.py
invitable/urls.py
invitable/views.py