Metadata-Version: 1.0
Name: django-invitable
Version: 0.1
Summary: Reusable invitations app for Django
Home-page: https://github.com/teodor-pripoae/django-invitable
Author: Teodor Pripoae
Author-email: toni@netbaiji.com
License: UNKNOWN
Platform: UNKNOWN
